tarragon.py
tarragon-0.1.0rc0.dist-info/LICENSE
tarragon-0.1.0rc0.dist-info/METADATA
tarragon-0.1.0rc0.dist-info/WHEEL
tarragon-0.1.0rc0.dist-info/RECORD
