Metadata-Version: 2.3
Name: tarragon
Version: 0.1.0rc0
Summary: Text analogue of dill library
License: AVL v1.0
Author: pyizi
Author-email: pyizi@proton.me
Requires-Python: >=3.12
Classifier: License :: Other/Proprietary License
Classifier: Programming Language :: Python :: 3
Classifier: Programming Language :: Python :: 3.12
Classifier: Programming Language :: Python :: 3.13
Project-URL: License, https://github.com/pyizi/tarragon?tab=License-1-ov-file
Project-URL: Repository, https://github.com/pyizi/tarragon
